[
    {
        "normalizedSource": "test",
        "displaySource": "test",
        "translations1": [],
        "translations": [
            {
                "normalizedTarget": "prueba",
                "displayTarget": "prueba",
                "posTag": "OTHER",
                "confidence": 0.7217,
                "prefixWord": "",
                "backTranslations": [
                    {
                        "normalizedText": "test",
                        "displayText": "test",
                        "numExamples": 1,
                        "frequencyCount": 87620
                    },
                    {
                        "normalizedText": "proof",
                        "displayText": "proof",
                        "numExamples": 1,
                        "frequencyCount": 17711
                    },
                    {
                        "normalizedText": "trial",
                        "displayText": "trial",
                        "numExamples": 1,
                        "frequencyCount": 12745
                    }
                ]
            },
            {
                "normalizedTarget": "probar",
                "displayTarget": "probar",
                "posTag": "VERB",
                "confidence": 0.1328,
                "prefixWord": "",
                "backTranslations": [
                    {
                        "normalizedText": "test",
                        "displayText": "test",
                        "numExamples": 1,
                        "frequencyCount": 16129
                    },
                    {
                        "normalizedText": "try",
                        "displayText": "try",
                        "numExamples": 1,
                        "frequencyCount": 15888
                    },
                    {
                        "normalizedText": "prove",
                        "displayText": "prove",
                        "numExamples": 1,
                        "frequencyCount": 5520
                    },
                    {
                        "normalizedText": "taste",
                        "displayText": "taste",
                        "numExamples": 1,
                        "frequencyCount": 1687
                    },
                    {
                        "normalizedText": "sample",
                        "displayText": "sample",
                        "numExamples": 1,
                        "frequencyCount": 1066
                    },
                    {
                        "normalizedText": "trial",
                        "displayText": "trial",
                        "numExamples": 0,
                        "frequencyCount": 463
                    }
                ]
            },
            {
                "normalizedTarget": "examen",
                "displayTarget": "examen",
                "posTag": "OTHER",
                "confidence": 0.0657,
                "prefixWord": "",
                "backTranslations": [
                    {
                        "normalizedText": "examination",
                        "displayText": "examination",
                        "numExamples": 1,
                        "frequencyCount": 16577
                    },
                    {
                        "normalizedText": "test",
                        "displayText": "test",
                        "numExamples": 0,
                        "frequencyCount": 7973
                    },
                    {
                        "normalizedText": "screening",
                        "displayText": "screening",
                        "numExamples": 0,
                        "frequencyCount": 734
                    }
                ]
            },
            {
                "normalizedTarget": "ensayo",
                "displayTarget": "ensayo",
                "posTag": "NOUN",
                "confidence": 0.0503,
                "prefixWord": "",
                "backTranslations": [
                    {
                        "normalizedText": "trial",
                        "displayText": "trial",
                        "numExamples": 1,
                        "frequencyCount": 6324
                    },
                    {
                        "normalizedText": "test",
                        "displayText": "test",
                        "numExamples": 1,
                        "frequencyCount": 6108
                    },
                    {
                        "normalizedText": "essay",
                        "displayText": "essay",
                        "numExamples": 1,
                        "frequencyCount": 3541
                    },
                    {
                        "normalizedText": "assay",
                        "displayText": "assay",
                        "numExamples": 1,
                        "frequencyCount": 1604
                    },
                    {
                        "normalizedText": "rehearsal",
                        "displayText": "rehearsal",
                        "numExamples": 1,
                        "frequencyCount": 1557
                    }
                ]
            },
            {
                "normalizedTarget": "análisis",
                "displayTarget": "análisis",
                "posTag": "NOUN",
                "confidence": 0.0295,
                "prefixWord": "",
                "backTranslations": [
                    {
                        "normalizedText": "review",
                        "displayText": "review",
                        "numExamples": 1,
                        "frequencyCount": 20711
                    },
                    {
                        "normalizedText": "test",
                        "displayText": "test",
                        "numExamples": 1,
                        "frequencyCount": 3582
                    },
                    {
                        "normalizedText": "analysis",
                        "displayText": "analysis",
                        "numExamples": 0,
                        "frequencyCount": 816
                    },
                    {
                        "normalizedText": "exploration",
                        "displayText": "exploration",
                        "numExamples": 1,
                        "frequencyCount": 180
                    }
                ]
            }
        ]
    }
]